CHANGES.rst
CONTRIBUTORS.rst
MANIFEST.in
README.rst
VERSION
setup.cfg
setup.py
docs/LICENSE.GPL
docs/LICENSE.rst
docs/index.rst
src/visaplan/__init__.py
src/visaplan.plone.breadcrumbs.egg-info/PKG-INFO
src/visaplan.plone.breadcrumbs.egg-info/SOURCES.txt
src/visaplan.plone.breadcrumbs.egg-info/dependency_links.txt
src/visaplan.plone.breadcrumbs.egg-info/entry_points.txt
src/visaplan.plone.breadcrumbs.egg-info/namespace_packages.txt
src/visaplan.plone.breadcrumbs.egg-info/not-zip-safe
src/visaplan.plone.breadcrumbs.egg-info/requires.txt
src/visaplan.plone.breadcrumbs.egg-info/top_level.txt
src/visaplan/plone/__init__.py
src/visaplan/plone/breadcrumbs/__init__.py
src/visaplan/plone/breadcrumbs/_vars.py
src/visaplan/plone/breadcrumbs/adapter.py
src/visaplan/plone/breadcrumbs/base.py.DELETEME
src/visaplan/plone/breadcrumbs/configure.zcml
src/visaplan/plone/breadcrumbs/tree.py
src/visaplan/plone/breadcrumbs/utils.py
src/visaplan/plone/breadcrumbs/base/__init__.py
src/visaplan/plone/breadcrumbs/base/_base.py
src/visaplan/plone/breadcrumbs/base/_context.py
src/visaplan/plone/breadcrumbs/base/_data.py
src/visaplan/plone/breadcrumbs/base/_devel.py
src/visaplan/plone/breadcrumbs/base/_edit.py
src/visaplan/plone/breadcrumbs/base/_exceptions.py
src/visaplan/plone/breadcrumbs/base/_info.py
src/visaplan/plone/breadcrumbs/base/_log.py
src/visaplan/plone/breadcrumbs/base/_par_naive.py
src/visaplan/plone/breadcrumbs/base/_registry.py
src/visaplan/plone/breadcrumbs/base/_rooted.py
src/visaplan/plone/breadcrumbs/base/_uncrumb.py
src/visaplan/plone/breadcrumbs/base/_view.py